{
  "name": "zevy-raylib",
  "owner": "captkirk88",
  "repo": "zevy-raylib",
  "description": "zevy-raylib is a abstraction for Raylib with zevy-ecs. It provides a plugin-based architecture for rapid game prototyping. (work in progress)",
  "type": "package",
  "topics": [
    "raylib-zig",
    "zig",
    "zig-library",
    "zig-package",
    "zevy-ecs",
    "raylib",
    "zevy"
  ],
  "stars": 5,
  "forks": 0,
  "watchers": 0,
  "updated_at": "2026-06-07T01:51:13Z",
  "dependencies": [
    {
      "name": "zevy_ecs",
      "url": "git+https://github.com/captkirk88/zevy-ecs#19d0b9b81802d8ad8ef7b9118b7dec95df731cd9",
      "hash": "zevy_ecs-3.0.3-VoL9mSNoCgD-7MLfzMaOqYl2p9HMRVpHC2-ej84joBU6"
    },
    {
      "name": "raylib_zig",
      "url": "git+https://github.com/raylib-zig/raylib-zig#97be2c7ae646a2f09856604b138c427c0af1b952",
      "hash": "raylib_zig-6.0.0-KE8REDJ4BQBu7lKwYNt6R4j5ywPeS37zqW6zrtjCcRwH"
    },
    {
      "name": "known_folders",
      "url": "git+https://github.com/ziglibs/known-folders#207c34a16e4365edc20d92c7892f962b3bed46e8",
      "hash": "known_folders-0.0.0-Fy-PJsbKAACbDh9bBxR0MMThxZSS6A9RH4apWphNHY70"
    },
    {
      "name": "xml",
      "url": "git+https://github.com/ianprime0509/zig-xml#b97f2ab4868ae3cac9902b33a40d3f31d2df739d",
      "hash": "xml-0.2.0-ZTbP3yI6AgB9Rpd2hQrueO63ib0Bm6mQiL_WB1t7JAmP"
    },
    {
      "name": "zevy_reflect",
      "url": "git+https://github.com/captkirk88/zevy-reflect#0b3f97b2de3cf16fab70eb337b830e80442dd535",
      "hash": "zevy_reflect-1.5.4-Ob80cCTFAwDLrmcP6XYM1F0JEZ6CMwBCxR6hc4DSxcpM"
    },
    {
      "name": "zevy_mem",
      "url": "git+https://github.com/captkirk88/zevy-mem#2e91ded097ded214a5127c907f2fae59f1f4e975",
      "hash": "zevy_mem-1.2.3-jK9L0WI_AwCKY26zPbmwvI51hJ7_J80TQk09tmOlVeph"
    },
    {
      "name": "zevy_buildtools",
      "url": "git+https://github.com/captkirk88/zevy-buildtools#ef611bb2308a577eca6c2cceba68bbdcab6e10e7",
      "hash": "zevy_buildtools-1.3.2-AG3r_IMOAQBvTaraIbje0VPv3I9jWxz67Cqoq4cr_Z_C"
    }
  ],
  "minimum_zig_version": "0.16.0",
  "readme": "# Zevy Raylib\n\n[license]: https://img.shields.io/github/license/captkirk88/zevy-raylib?style=for-the-badge&logo=opensourcehardware&label=License&logoColor=C0CAF5&labelColor=414868&color=8c73cc\n\n[![][license]](https://github.com/captkirk88/zevy-raylib/blob/main/LICENSE)\n\n[![Zig Version](https://img.shields.io/badge/zig-0.16.0-blue.svg)](https://ziglang.org/)\n\n> [!WARNING]\n> This library and its APIs are experimental.\n> The API and internal behavior can and will change without backward compatibility guarantees.\n> Tests and cross-platform coverage are limited — treat this as a development-ready library, not production-ready.\n> Please open issues or submit PRs if you rely on features that should be stabilized or suggested.\n\n### Table of contents\n\n- [Introduction](#introduction)\n- [Quick Start](#quick-start)\n- [Contributing](#contributing)\n- [Projects](#projects)\n- [License](#license)\n\n---\n\n## Introduction\n\nZevy Raylib is a small library that wires the Raylib runtime into a Zevy ECS-based app. It handles window creation, input harvesting, asset management and sets up RayGui-based UI systems with multiple layout options.\n\n---\n\n## Quick Start\n\n[Examples](examples/) can be ran with:\n\n```bash\nzig build examples\n```\n\n> [!NOTE]\n> Requires `libgl-dev libx11-dev libxrandr-dev libxinerama-dev libxi-dev libxcursor-dev` on Linux.\n\n---\n\n## Contributing\n\n- Follow existing Zig patterns\n- Register new plugins in `src/root.zig` by adding them to `plug()`\n- Add unit tests beside features in the `src/*` directory. Prefer tests to be named `*_tests.zig`.\n\n## Projects\n- [zevy-alloy](https://github.com/captkirk88/zevy-alloy)\n- [zevy-ecs](https://github.com/captkirk88/zevy-ecs)\n\n## License\n[MIT](LICENSE)",
  "owner_avatar_url": "https://avatars.githubusercontent.com/u/6296457?u=57a7319f473f4c068419efb04c3c3b0f54a42efe&v=4",
  "releases": [],
  "owner_bio": "Am I A.I?",
  "owner_company": "Evil Lair",
  "owner_location": "Moon",
  "owner_blog": null,
  "owner_twitter_username": null,
  "owner_followers": 7,
  "owner_following": 15,
  "owner_created_at": "2014-01-01T08:56:32Z",
  "category": "library"
}