{
  "name": "ziter",
  "owner": "Hejsil",
  "repo": "ziter",
  "description": "The missing iterators for Zig",
  "type": "package",
  "topics": [
    "zig-package",
    "zig",
    "iterator",
    "functional",
    "iterator-library",
    "iterators",
    "zig-library"
  ],
  "stars": 81,
  "forks": 2,
  "watchers": 3,
  "updated_at": "2025-11-29T09:49:17Z",
  "minimum_zig_version": "0.14.0",
  "readme": "# ziter\n\nAn iterator library for zig inspired by the iterators in the Rust standard libary.\n\n```zig\nconst iter = @import(\"ziter\");\nconst std = @import(\"std\");\n\ntest \"ascii\" {\n    const ascii_digits = iter.range(u8, 0, 255)\n        .filter({}, iter.void_ctx(std.ascii.isDigit));\n\n    const ascii_alpha = try iter.range(u8, 0, 255)\n        .filter({}, iter.void_ctx(std.ascii.isAlphabetic))\n        .collect_no_allocator(std.BoundedArray(u8, 255){});\n\n    try iter.expectEqual(iter.deref(\"0123456789\"), ascii_digits);\n    try std.testing.expectEqualStrings(\n        \"ABCDEFGHIJKLMNOPQRSTUVWXYZabcdefghijklmnopqrstuvwxyz\",\n        ascii_alpha.slice(),\n    );\n}\n\ntest \"Fibonacci\" {\n    const fib = Fibonacci{};\n\n    const fib_sum_first_5 = fib.take(5).sum(usize);\n    const fib_first_alphabetic = fib.map({}, to_u8)\n        .find({}, iter.void_ctx(std.ascii.isAlphabetic));\n\n    try std.testing.expectEqual(@as(usize, 7), fib_sum_first_5);\n    try std.testing.expectEqual(@as(?u8, 'Y'), fib_first_alphabetic);\n}\n\npub const Fibonacci = struct {\n    c: usize = 0,\n    n: usize = 1,\n\n    pub fn next(it: *@This()) ?usize {\n        const curr = it.c;\n        it.c = it.n;\n        it.n = curr + it.n;\n        return curr;\n    }\n\n    pub usingnamespace iter;\n};\n\nfn to_u8(_: void, item: usize) u8 {\n    return @truncate(item);\n}\n\n```\n\n",
  "owner_avatar_url": "https://avatars.githubusercontent.com/u/3759175?u=d5da2f7afbb8ffadbc68b1822d16b107da36b4de&v=4",
  "releases": [],
  "owner_bio": "Makes computers go brrrrr",
  "owner_company": null,
  "owner_location": "Celadon City",
  "owner_blog": "https://hejsil.github.io",
  "owner_twitter_username": null,
  "owner_followers": 394,
  "owner_following": 25,
  "owner_created_at": "2013-03-03T23:32:52Z",
  "license": "MIT",
  "category": "library"
}